detokenize/__init__.py
detokenize/detokenizer.py
detokenize-0.0.4.dist-info/LICENSE
detokenize-0.0.4.dist-info/METADATA
detokenize-0.0.4.dist-info/WHEEL
detokenize-0.0.4.dist-info/top_level.txt
detokenize-0.0.4.dist-info/RECORD
