Metadata-Version: 2.1
Name: detokenize
Version: 0.0.4
Summary: Package to detokenize the stream of tokens
Author-email: Littin Rajan <littinrajan@gmail.com>
Project-URL: Homepage, https://github.com/littinrajan/detokenize
Project-URL: Repository, https://github.com/littinrajan/detokenize
Project-URL: Bug Tracker, https://github.com/littinrajan/detokenize/issues
Classifier: Programming Language :: Python :: 3
Classifier: License :: OSI Approved :: MIT License
Classifier: Operating System :: OS Independent
Requires-Python: >=3.7
License-File: LICENSE
